bdbag/__init__.py
bdbag/bdbag_api.py
bdbag/bdbag_cli.py
bdbag/bdbag_config.py
bdbag/bdbag_ro.py
bdbag/bdbag_utils.py
bdbag/bdbagit.py
bdbag/bdbagit_profile.py
bdbag/fetch/__init__.py
bdbag/fetch/fetcher.py
bdbag/fetch/auth/__init__.py
bdbag/fetch/auth/cookies.py
bdbag/fetch/auth/keychain.py
bdbag/fetch/resolvers/__init__.py
bdbag/fetch/resolvers/ark_resolver.py
bdbag/fetch/resolvers/base_resolver.py
bdbag/fetch/resolvers/dataguid_resolver.py
bdbag/fetch/resolvers/doi_resolver.py
bdbag/fetch/transports/__init__.py
bdbag/fetch/transports/base_transport.py
bdbag/fetch/transports/fetch_boto3.py
bdbag/fetch/transports/fetch_ftp.py
bdbag/fetch/transports/fetch_gcs.py
bdbag/fetch/transports/fetch_globus.py
bdbag/fetch/transports/fetch_http.py
bdbag/fetch/transports/fetch_tag.py
bdbag-1.8.0.dist-info/licenses/LICENSE
examples/bagofbags/bagofbags.py
bdbag-1.8.0.dist-info/METADATA
bdbag-1.8.0.dist-info/WHEEL
bdbag-1.8.0.dist-info/entry_points.txt
bdbag-1.8.0.dist-info/top_level.txt
bdbag-1.8.0.dist-info/RECORD
