Metadata-Version: 2.4
Name: bdbag
Version: 1.8.0
Summary: Big Data Bag Utilities
Author: Mike D'Arcy
Maintainer-email: "USC Information Sciences Institute, Informatics Systems Research Division" <isrd-support@isi.edu>
Classifier: Intended Audience :: Science/Research
Classifier: Intended Audience :: Developers
Classifier: Operating System :: POSIX
Classifier: Operating System :: MacOS :: MacOS X
Classifier: Operating System :: Microsoft :: Windows
Classifier: License :: OSI Approved :: Apache Software License
Classifier: Programming Language :: Python
Classifier: Programming Language :: Python :: 3.8
Classifier: Programming Language :: Python :: 3.9
Classifier: Programming Language :: Python :: 3.10
Classifier: Programming Language :: Python :: 3.11
Classifier: Programming Language :: Python :: 3.12
Requires-Python: <4,>=3.8
License-File: LICENSE
Requires-Dist: pytz
Requires-Dist: tzlocal
Requires-Dist: certifi
Requires-Dist: packaging
Requires-Dist: requests
Requires-Dist: bagit==1.9.0
Requires-Dist: bagit-profile==1.3.1
Provides-Extra: boto
Requires-Dist: boto3>=1.9.5; extra == "boto"
Requires-Dist: botocore; extra == "boto"
Requires-Dist: awscli; extra == "boto"
Provides-Extra: globus
Requires-Dist: globus_sdk<4,>=2; extra == "globus"
Provides-Extra: gcs
Requires-Dist: google_cloud_storage; extra == "gcs"
Dynamic: license-file
